tinted/__init__.py
tinted/__main__.py
tinted/core.py
tinted/sequences.py
tinted-1.0.1.dist-info/LICENSE
tinted-1.0.1.dist-info/METADATA
tinted-1.0.1.dist-info/WHEEL
tinted-1.0.1.dist-info/entry_points.txt
tinted-1.0.1.dist-info/top_level.txt
tinted-1.0.1.dist-info/RECORD
