Metadata-Version: 2.1
Name: tinted
Version: 1.0.1
Summary: Give your print output the tint it deserves!
Home-page: https://github.com/MystPi/tinted
Author: MystPi
License: MIT
Platform: UNKNOWN
Classifier: License :: OSI Approved :: MIT License
Classifier: Programming Language :: Python :: 3
Classifier: Programming Language :: Python :: 3.7
License-File: LICENSE
